tempbeat/__init__.py
tempbeat/skeleton.py
tempbeat/evaluation/compare_bpm.py
tempbeat/evaluation/error.py
tempbeat/extraction/anomaly_treatment.py
tempbeat/extraction/correlation.py
tempbeat/extraction/heartbeat_extraction.py
tempbeat/extraction/interval_conversion.py
tempbeat/extraction/mod_fixpeaks.py
tempbeat/extraction/segmentation.py
tempbeat/extraction/template_generation.py
tempbeat/utils/interpolation.py
tempbeat/utils/matlab_utils.py
tempbeat/utils/misc_utils.py
tempbeat/utils/resampling.py
tempbeat/utils/timestamp.py
tempbeat-0.0.3.dist-info/LICENSE.txt
tempbeat-0.0.3.dist-info/METADATA
tempbeat-0.0.3.dist-info/WHEEL
tempbeat-0.0.3.dist-info/top_level.txt
tempbeat-0.0.3.dist-info/RECORD
