Metadata-Version: 2.1
Name: tempbeat
Version: 0.0.3
Summary: Template-based in-ear heartbeat extraction
Home-page: https://github.com/danibene/tempbeat/
Author: danibene
Author-email: 34680344+danibene@users.noreply.github.com
License: MIT
Project-URL: Documentation, https://pyscaffold.org/
Platform: any
Classifier: Development Status :: 4 - Beta
Classifier: Programming Language :: Python
Requires-Python: >=3.8
License-File: LICENSE.txt
Requires-Dist: numpy
Requires-Dist: pandas
Requires-Dist: matplotlib
Requires-Dist: neurokit2
Requires-Dist: json-tricks
Requires-Dist: importlib-metadata ; python_version < "3.8"
Provides-Extra: testing
Requires-Dist: setuptools ; extra == 'testing'
Requires-Dist: pytest ; extra == 'testing'
Requires-Dist: pytest-cov ; extra == 'testing'
Requires-Dist: requests ; extra == 'testing'
